eyeflow_sdk/__init__.py
eyeflow_sdk/data_augmentation_default_parms.json
eyeflow_sdk/dataset_default_parms.json
eyeflow_sdk/dataset_serialize_pb2.py
eyeflow_sdk/dataset_types.json
eyeflow_sdk/dataset_utils.py
eyeflow_sdk/edge_client.py
eyeflow_sdk/eyeflow_conf.json
eyeflow_sdk/eyeflow_conf.yaml
eyeflow_sdk/eyeflow_conf_example.yaml
eyeflow_sdk/file_access.py
eyeflow_sdk/img_utils.py
eyeflow_sdk/jetson_utils.py
eyeflow_sdk/log_obj.py
eyeflow_sdk/message_queue.py
eyeflow_sdk/metrics.py
eyeflow_sdk/network_default_parms.json
eyeflow_sdk/nv_gpu.py
eyeflow_sdk/reset_usb.py
eyeflow_sdk/token_utils.py
eyeflow_sdk/video_log.py
eyeflow_sdk/video_play.py
eyeflow_sdk/visualization.py
eyeflow_sdk/cloud_store/__init__.py
eyeflow_sdk/cloud_store/azure.py
eyeflow_sdk-1.2.9.dist-info/LICENSE
eyeflow_sdk-1.2.9.dist-info/METADATA
eyeflow_sdk-1.2.9.dist-info/WHEEL
eyeflow_sdk-1.2.9.dist-info/top_level.txt
eyeflow_sdk-1.2.9.dist-info/RECORD
