Metadata-Version: 2.1
Name: eyeflow-sdk
Version: 1.2.9
Summary: Functions and classes for development of Eyeflow Applications
Home-page: https://github.com/siliconlife-ai/eyeflow_sdk-pkg
Author: Eyeflow.AI
Author-email: support@eyeflow.ai
Classifier: Programming Language :: Python :: 3
Classifier: License :: OSI Approved :: MIT License
Classifier: Operating System :: OS Independent
Requires-Python: >=3.8
License-File: LICENSE
Requires-Dist: python-dateutil
Requires-Dist: pymongo
Requires-Dist: dnspython
Requires-Dist: pika
Requires-Dist: numpy
Requires-Dist: opencv-python
Requires-Dist: pillow
Requires-Dist: protobuf
Requires-Dist: h5py
Requires-Dist: arrow
Requires-Dist: psutil
Requires-Dist: pynvml
Requires-Dist: xmltodict
Requires-Dist: pyyaml
Requires-Dist: pyjwt
Requires-Dist: azure-storage-blob
